rotate_volume/__init__.py
rotate_volume/rotate_volume.py
rotate_volume-0.0.0.dist-info/LICENSE
rotate_volume-0.0.0.dist-info/METADATA
rotate_volume-0.0.0.dist-info/WHEEL
rotate_volume-0.0.0.dist-info/RECORD
