Metadata-Version: 2.3
Name: rotate-volume
Version: 0.0.0
Summary: An efficient volume rotation algorithm based on Cupy.
License: MIT
Author: GGN_2015
Author-email: neko@jlulug.org
Requires-Python: >=3.10, <3.13
Classifier: License :: OSI Approved :: MIT License
Classifier: Programming Language :: Python :: 3
Classifier: Programming Language :: Python :: 3.10
Classifier: Programming Language :: Python :: 3.11
Classifier: Programming Language :: Python :: 3.12
Requires-Dist: cupy (>=13.6.0,<14.0.0)
